fretty/__init__.py
fretty/__main__.py
fretty/fretty.py
fretty-2.0.1.dist-info/LICENSE
fretty-2.0.1.dist-info/METADATA
fretty-2.0.1.dist-info/WHEEL
fretty-2.0.1.dist-info/entry_points.txt
fretty-2.0.1.dist-info/top_level.txt
fretty-2.0.1.dist-info/RECORD
