Metadata-Version: 2.1
Name: fretty
Version: 2.0.1
Summary: Fretty is a guitar fretboard generator
Home-page: https://github.com/thomasvolk/fretty
Author: Thomas Volk
Author-email: info@thomasvolk.de
License: Apache
Platform: any
Classifier: Programming Language :: Python :: 3.9
Classifier: License :: OSI Approved :: Apache Software License
Classifier: Operating System :: OS Independent
Classifier: Topic :: Text Processing :: Markup
Requires-Python: >=3.9.0
License-File: LICENSE
Provides-Extra: png
Requires-Dist: CairoSVG ; extra == 'png'
